.gitignore
PKG-INFO
pyproject.toml
pytest_bec_e2e/__init__.py
pytest_bec_e2e/plugin.py
pytest_bec_e2e-3.94.0.dist-info/METADATA
pytest_bec_e2e-3.94.0.dist-info/WHEEL
pytest_bec_e2e-3.94.0.dist-info/entry_points.txt
pytest_bec_e2e-3.94.0.dist-info/RECORD
