Metadata-Version: 2.4
Name: pytest-bec-e2e
Version: 3.94.0
Summary: BEC pytest plugin for end-to-end tests
Project-URL: Bug Tracker, https://github.com/bec-project/bec/issues
Project-URL: Homepage, https://github.com/bec-project/bec
Classifier: Development Status :: 3 - Alpha
Classifier: Programming Language :: Python :: 3
Classifier: Topic :: Scientific/Engineering
Requires-Python: >=3.11
Requires-Dist: bec-ipython-client
Requires-Dist: bec-lib
Requires-Dist: bec-server
Requires-Dist: pytest
Requires-Dist: pytest-redis
